[
    {
        "tagline": "Cказачное заморкское явство",
        "title": "Нямушка",
        "subtitle": "с фуа-гра",
        "contents": [
            "10 порций", "мышь в подарок"
        ],
        "width": 0.5,
        "description": "Печень утки разварная с артишоками.",
        "availability": false
    },
    {
        "tagline": "Cказачное заморкское явство",
        "title": "Нямушка",
        "subtitle": "с рыбой",
        "contents": [
            "40 порций", "2 мыши в подарок"
        ],
        "width": 2,
        "description": "Головы щучьи с чесноком да свежайшая сёмгушка.",
        "availability": false
    },
    {
        "tagline": "Cказачное заморкское явство",
        "title": "Нямушка",
        "subtitle": "с курой",
        "contents": [
            "100 порций", "5 мышей в подарок", "заказчик доволен"
        ],
        "width": 5,
        "description": "Филе из цыплят с трюфелями в бульоне.",
        "availability": true
    }
]